vecorel_cli/__init__.py
vecorel_cli/basecommand.py
vecorel_cli/const.py
vecorel_cli/convert.py
vecorel_cli/converters.py
vecorel_cli/create_geojson.py
vecorel_cli/create_geoparquet.py
vecorel_cli/create_jsonschema.py
vecorel_cli/create_stac.py
vecorel_cli/describe.py
vecorel_cli/improve.py
vecorel_cli/merge.py
vecorel_cli/registry.py
vecorel_cli/rename_extension.py
vecorel_cli/validate.py
vecorel_cli/validate_schema.py
vecorel_cli/cli/__init__.py
vecorel_cli/cli/logger.py
vecorel_cli/cli/options.py
vecorel_cli/cli/path_url.py
vecorel_cli/cli/setup.py
vecorel_cli/cli/util.py
vecorel_cli/conversion/__init__.py
vecorel_cli/conversion/admin.py
vecorel_cli/conversion/base.py
vecorel_cli/datasets/__init__.py
vecorel_cli/datasets/template.py
vecorel_cli/encoding/__init__.py
vecorel_cli/encoding/auto.py
vecorel_cli/encoding/base.py
vecorel_cli/encoding/geojson.py
vecorel_cli/encoding/geoparquet.py
vecorel_cli/jsonschema/__init__.py
vecorel_cli/jsonschema/template.py
vecorel_cli/parquet/__init__.py
vecorel_cli/parquet/geopandas.py
vecorel_cli/parquet/types.py
vecorel_cli/validation/__init__.py
vecorel_cli/validation/base.py
vecorel_cli/validation/data.py
vecorel_cli/validation/geojson.py
vecorel_cli/validation/geoparquet.py
vecorel_cli/vecorel/__init__.py
vecorel_cli/vecorel/collection.py
vecorel_cli/vecorel/extensions.py
vecorel_cli/vecorel/ops.py
vecorel_cli/vecorel/schemas.py
vecorel_cli/vecorel/typing.py
vecorel_cli/vecorel/util.py
vecorel_cli/vecorel/version.py
vecorel_cli-0.2.12.dist-info/licenses/LICENSE
vecorel_cli-0.2.12.dist-info/METADATA
vecorel_cli-0.2.12.dist-info/WHEEL
vecorel_cli-0.2.12.dist-info/entry_points.txt
vecorel_cli-0.2.12.dist-info/top_level.txt
vecorel_cli-0.2.12.dist-info/RECORD
