Metadata-Version: 2.4
Name: vecorel-cli
Version: 0.2.12
Summary: CLI tools such as validation and file format conversion for vecorel.
Author: Matthias Mohr
License-Expression: Apache-2.0
Project-URL: Homepage, https://github.com/vecorel/cli
Project-URL: Bug Reports, https://github.com/vecorel/cli/issues
Project-URL: Source, https://github.com/vecorel/cli
Classifier: Development Status :: 4 - Beta
Classifier: Programming Language :: Python :: 3
Classifier: Programming Language :: Python :: 3.10
Classifier: Programming Language :: Python :: 3.11
Classifier: Programming Language :: Python :: 3.12
Classifier: Programming Language :: Python :: 3.13
Requires-Python: <3.14,>=3.10
License-File: LICENSE
Requires-Dist: pyyaml<7.0,>=6.0
Requires-Dist: click<9.0,>=8.1
Requires-Dist: geopandas<2.0,>=1.0.0
Requires-Dist: requests<3.0,>=2.30
Requires-Dist: shapely<3.0,>=2.1
Requires-Dist: numpy<2.2,>=2.0
Requires-Dist: pyarrow<22.0,>=21.0
Requires-Dist: py7zr<2.0,>=1.0
Requires-Dist: fsspec==2025.7.0
Requires-Dist: jsonschema[format]<5.0,>=4.20
Requires-Dist: aiohttp<4.0,>=3.9
Requires-Dist: yarl<2.0,>=1.20
Requires-Dist: rarfile<5.0,>=4.0
Requires-Dist: semantic-version<3.0,>=2.10.0
Requires-Dist: json-stream<3.0,>=2.3.0
Requires-Dist: flatdict<5.0,>=4.0
Requires-Dist: loguru==0.7.3
Dynamic: license-file
